simple_math/__init__.py
simple_math/operations.py
simple_math10000-0.1.0.dist-info/LICENSE.txt
simple_math10000-0.1.0.dist-info/METADATA
simple_math10000-0.1.0.dist-info/WHEEL
simple_math10000-0.1.0.dist-info/top_level.txt
simple_math10000-0.1.0.dist-info/RECORD
